pyhearingai/README.md
pyhearingai/__init__.py
pyhearingai/application/__init__.py
pyhearingai/application/outputs.py
pyhearingai/application/transcribe.py
pyhearingai/cli.py
pyhearingai/core/__init__.py
pyhearingai/core/models.py
pyhearingai/core/ports.py
pyhearingai/infrastructure/__init__.py
pyhearingai/infrastructure/adapters.py
pyhearingai/infrastructure/audio_converter.py
pyhearingai/infrastructure/diarizers/__init__.py
pyhearingai/infrastructure/diarizers/pyannote.py
pyhearingai/infrastructure/formatters/__init__.py
pyhearingai/infrastructure/formatters/json.py
pyhearingai/infrastructure/formatters/markdown.py
pyhearingai/infrastructure/formatters/srt.py
pyhearingai/infrastructure/formatters/text.py
pyhearingai/infrastructure/formatters/vtt.py
pyhearingai/infrastructure/registry.py
pyhearingai/infrastructure/speaker_assignment.py
pyhearingai/infrastructure/speaker_assignment_gpt.py
pyhearingai/infrastructure/transcribers/__init__.py
pyhearingai/infrastructure/transcribers/whisper_openai.py
pyhearingai/presentation/__init__.py
pyhearingai-0.1.0.dist-info/LICENSE
pyhearingai-0.1.0.dist-info/METADATA
pyhearingai-0.1.0.dist-info/WHEEL
pyhearingai-0.1.0.dist-info/entry_points.txt
pyhearingai-0.1.0.dist-info/RECORD
