Metadata-Version: 2.3
Name: pyhearingai
Version: 0.1.0
Summary: Library for transcribing audio conversations with accurate speaker identification
License: Apache-2.0
Author: MDGrey33
Author-email: roland@abouyounes.com
Requires-Python: >=3.8,<4.0
Classifier: Development Status :: 3 - Alpha
Classifier: Intended Audience :: Developers
Classifier: License :: OSI Approved :: Apache Software License
Classifier: Programming Language :: Python :: 3
Classifier: Programming Language :: Python :: 3.8
Classifier: Programming Language :: Python :: 3.9
Classifier: Programming Language :: Python :: 3.10
Classifier: Programming Language :: Python :: 3.11
Classifier: Programming Language :: Python :: 3.12
Classifier: Programming Language :: Python :: 3.13
Classifier: Topic :: Multimedia :: Sound/Audio :: Speech
Provides-Extra: gpu
Requires-Dist: ffmpeg-python (>=0.2.0,<0.3.0)
Requires-Dist: numpy (>=1.24.0,<2.0.0)
Requires-Dist: onnxruntime (>=1.20.1,<2.0.0)
Requires-Dist: openai (>=1.0.0,<2.0.0)
Requires-Dist: pyannote-audio (>=3.0.0,<4.0.0)
Requires-Dist: pydub (>=0.25.1,<0.26.0)
Requires-Dist: python-dotenv (>=1.0.0,<2.0.0)
Requires-Dist: requests (>=2.31.0,<3.0.0)
Requires-Dist: torch (>=2.0.0) ; extra == "gpu"
Project-URL: Repository, https://github.com/MDGrey33/PyHearingAI
